httpreverse/__init__.py
httpreverse/httpreverse.py
httpreverse/util.py
httpreverse-0.4.0.dist-info/DESCRIPTION.rst
httpreverse-0.4.0.dist-info/METADATA
httpreverse-0.4.0.dist-info/RECORD
httpreverse-0.4.0.dist-info/WHEEL
httpreverse-0.4.0.dist-info/metadata.json
httpreverse-0.4.0.dist-info/top_level.txt
