Metadata-Version: 2.0
Name: httpreverse
Version: 0.4.0
Summary: Reverse-engineer legacy HTTP APIs
Home-page: https://github.com/koodaamo/httpreverse
Author: Petri Savolainen
Author-email: petri@koodaamo.fi
License: GNU General Public License v3
Keywords: httpreverse
Platform: UNKNOWN
Classifier: Development Status :: 2 - Pre-Alpha
Classifier: Intended Audience :: Developers
Classifier: License :: OSI Approved :: GNU General Public License v3 (GPLv3)
Classifier: Natural Language :: English
Classifier: Programming Language :: Python :: 3
Classifier: Programming Language :: Python :: 3.6
Requires-Dist: jinja2
Requires-Dist: pyaml
Requires-Dist: xmltodict
